biotmed_facade_sdk/__init__.py
biotmed_facade_sdk/api_client.py
biotmed_facade_sdk/api_response.py
biotmed_facade_sdk/configuration.py
biotmed_facade_sdk/exceptions.py
biotmed_facade_sdk/py.typed
biotmed_facade_sdk/rest.py
biotmed_facade_sdk/api/__init__.py
biotmed_facade_sdk/api/health_check_api_api.py
biotmed_facade_sdk/api/patient_sign_up_api_api.py
biotmed_facade_sdk/models/__init__.py
biotmed_facade_sdk/models/address.py
biotmed_facade_sdk/models/assign_device_facade_request.py
biotmed_facade_sdk/models/basic_entity_data.py
biotmed_facade_sdk/models/basic_referenced_entity_data_uuidid.py
biotmed_facade_sdk/models/basic_template_data.py
biotmed_facade_sdk/models/connection_status.py
biotmed_facade_sdk/models/device_operational_status_response.py
biotmed_facade_sdk/models/device_response.py
biotmed_facade_sdk/models/device_status.py
biotmed_facade_sdk/models/error_response.py
biotmed_facade_sdk/models/mfa_dto.py
biotmed_facade_sdk/models/name.py
biotmed_facade_sdk/models/parent_template_response.py
biotmed_facade_sdk/models/patient_anonymous_self_sign_up_facade_request.py
biotmed_facade_sdk/models/patient_response.py
biotmed_facade_sdk/models/patient_self_sign_up_facade_request.py
biotmed_facade_sdk/models/patient_self_sign_up_facade_response.py
biotmed_facade_sdk/models/reference_attribute_uuidid_request.py
biotmed_facade_sdk/models/referenced_side_attribute_information.py
biotmed_facade_sdk/models/version_response.py
biotmed_facade_sdk-2.3.40.dist-info/METADATA
biotmed_facade_sdk-2.3.40.dist-info/WHEEL
biotmed_facade_sdk-2.3.40.dist-info/top_level.txt
biotmed_facade_sdk-2.3.40.dist-info/RECORD
